xbutil_gui/__init__.py
xbutil_gui/device_manager.py
xbutil_gui/plot_metrics.py
xbutil_gui/xbutil_gui.py
xbutil_gui/xbutil_handler.py
xbutil_gui/xbutil_top.py
xbutil_gui/resources/alveo-specifications.json
xbutil_gui/resources/xbutil-gui-config.json
xbutil_gui/resources/xbutil-icon.gif
xbutil_gui-0.0.8.dist-info/LICENSE
xbutil_gui-0.0.8.dist-info/METADATA
xbutil_gui-0.0.8.dist-info/WHEEL
xbutil_gui-0.0.8.dist-info/entry_points.txt
xbutil_gui-0.0.8.dist-info/top_level.txt
xbutil_gui-0.0.8.dist-info/RECORD
