Metadata-Version: 2.1
Name: xbutil-gui
Version: 0.0.8
Summary: Xilinx xbutil GUI
Home-page: https://github.com/jimw567/xbutil-gui
Author: Jim Wu
Author-email: jimw567@gmail.com
License: UNKNOWN
Platform: UNKNOWN
Classifier: Programming Language :: Python :: 3
Classifier: License :: OSI Approved :: MIT License
Classifier: Operating System :: OS Independent
Requires-Dist: pandas
Requires-Dist: matplotlib
Requires-Dist: tksheet
